akride/__init__.py
akride/background_task_manager.py
akride/client.py
akride/main.py
akride/_utils/__init__.py
akride/_utils/background_task_helper.py
akride/_utils/class_executor.py
akride/_utils/common_utils.py
akride/_utils/dataset_utils.py
akride/_utils/docker_image_utils.py
akride/_utils/exception_utils.py
akride/_utils/job_creator.py
akride/_utils/platform.py
akride/_utils/progress_bar_helper.py
akride/_utils/proxy_utils.py
akride/_utils/resource_utils.py
akride/_utils/shell_utils.py
akride/_utils/workflow_helper.py
akride/_utils/catalog/__init__.py
akride/_utils/catalog/catalog_tables_helper.py
akride/_utils/catalog/dataset_tables_info.py
akride/_utils/catalog/enums.py
akride/_utils/catalog/pipeline_tables_info.py
akride/_utils/catalog/string_utils.py
akride/_utils/catalog/tables_info.py
akride/_utils/pipeline/__init__.py
akride/_utils/pipeline/constants.py
akride/_utils/pipeline/pipeline_helper.py
akride/_utils/progress_manager/__init__.py
akride/_utils/progress_manager/manager.py
akride/_utils/progress_manager/progress_step.py
akride/_utils/video_splitter/__init__.py
akride/_utils/video_splitter/models.py
akride/_utils/video_splitter/split_video.sh
akride/_utils/video_splitter/splitter.py
akride/core/__init__.py
akride/core/_log.py
akride/core/_pipeline_executor.py
akride/core/constants.py
akride/core/enums.py
akride/core/exceptions.py
akride/core/types.py
akride/core/_entity_managers/__init__.py
akride/core/_entity_managers/catalog_manager.py
akride/core/_entity_managers/container_manager.py
akride/core/_entity_managers/dataset_manager.py
akride/core/_entity_managers/docker_image_manager.py
akride/core/_entity_managers/job_manager.py
akride/core/_entity_managers/manager.py
akride/core/_entity_managers/pipeline_manager.py
akride/core/_entity_managers/repository_manager.py
akride/core/_entity_managers/resultset_manager.py
akride/core/_entity_managers/sms_manager.py
akride/core/_entity_managers/subscriptions_manager.py
akride-0.7.3.dist-info/LICENSE.txt
akride-0.7.3.dist-info/METADATA
akride-0.7.3.dist-info/WHEEL
akride-0.7.3.dist-info/entry_points.txt
akride-0.7.3.dist-info/top_level.txt
akride-0.7.3.dist-info/RECORD
