Metadata-Version: 2.1
Name: akride
Version: 0.7.3
Summary: Data Explorer Client SDK
Home-page: https://github.com/akridata-ai/akride-examples
License: Proprietary
Project-URL: Documentation, https://akridata-akride.readthedocs-hosted.com/en/latest/
Platform: any
Classifier: Development Status :: 4 - Beta
Classifier: Programming Language :: Python
License-File: LICENSE.txt
Requires-Dist: importlib-metadata
Requires-Dist: akridata-akrimanager-v2 <1.26.0.dev0,>=1.25.0.dev0
Requires-Dist: akridata-dsp <2.17.0.dev0,>=2.16.0.dev0
Requires-Dist: attrs >=23.1.0
Requires-Dist: yarl >=1.9.2
Requires-Dist: tqdm >=4.66.1
Requires-Dist: pydantic <3,>=2
Requires-Dist: sink-writer-filters <1.26.0.dev0,>=1.25.0.dev0
Provides-Extra: cpu
Requires-Dist: pyakri-de-filters[cpu] <1.26.0.dev0,>=1.25.0.dev0 ; extra == 'cpu'
Requires-Dist: pyakri-de-utils[cpu] <1.26.0.dev0,>=1.25.0.dev0 ; extra == 'cpu'
Provides-Extra: gpu
Requires-Dist: pyakri-de-filters[gpu] <1.26.0.dev0,>=1.25.0.dev0 ; extra == 'gpu'
Requires-Dist: pyakri-de-utils[gpu] <1.26.0.dev0,>=1.25.0.dev0 ; extra == 'gpu'
Provides-Extra: testing
Requires-Dist: setuptools ; extra == 'testing'
Requires-Dist: pytest ; extra == 'testing'
Requires-Dist: pytest-cov ; extra == 'testing'
Requires-Dist: pytest-vcr ; extra == 'testing'
Requires-Dist: pytest-xdist ; extra == 'testing'
Requires-Dist: mockito ; extra == 'testing'
Requires-Dist: boto3 ; extra == 'testing'
